slack_bots/__init__.py
slack_bots/_version.py
slack_bots/py.typed
slack_bots/slack_bot.py
slack_bots/slack_event_bot.py
slack_bots/slack_rtm_bot.py
slack_bots-0.1.3.dist-info/LICENSE
slack_bots-0.1.3.dist-info/METADATA
slack_bots-0.1.3.dist-info/NOTICE
slack_bots-0.1.3.dist-info/WHEEL
slack_bots-0.1.3.dist-info/top_level.txt
slack_bots-0.1.3.dist-info/RECORD
