Metadata-Version: 2.1
Name: slack-bots
Version: 0.1.3
Summary: Collection of simple and reusable Slack bot prototypes.
Home-page: https://github.com/mbdevpl/slack-bots
Download-URL: 
Author: Mateusz Bysiek
Author-email: mateusz.bysiek@gmail.com
Maintainer: Mateusz Bysiek
Maintainer-email: mateusz.bysiek@gmail.com
License: Apache License 2.0
Keywords: bot,bots,chat,slack
Classifier: Development Status :: 1 - Planning
Classifier: Environment :: Console
Classifier: Intended Audience :: Developers
Classifier: License :: OSI Approved :: Apache Software License
Classifier: Natural Language :: English
Classifier: Operating System :: MacOS :: MacOS X
Classifier: Operating System :: Microsoft :: Windows
Classifier: Operating System :: POSIX :: Linux
Classifier: Programming Language :: Python :: 3.11
Classifier: Programming Language :: Python :: 3 :: Only
Classifier: Topic :: Utilities
Requires-Python: >=3.11
License-File: LICENSE
License-File: NOTICE
Requires-Dist: slackclient ~=2.9
Requires-Dist: slackeventsapi ~=3.0
Requires-Dist: version-query ~=1.5
